rinokeras/__init__.py
rinokeras/compat/__init__.py
rinokeras/compat/distributed.py
rinokeras/compat/py34_utils.py
rinokeras/compat/py35_utils.py
rinokeras/compat/utils.py
rinokeras/core/__init__.py
rinokeras/core/v1x/__init__.py
rinokeras/core/v1x/common/__init__.py
rinokeras/core/v1x/common/attention.py
rinokeras/core/v1x/common/distributions.py
rinokeras/core/v1x/common/gcn.py
rinokeras/core/v1x/common/losses.py
rinokeras/core/v1x/common/optimizers.py
rinokeras/core/v1x/common/rnn.py
rinokeras/core/v1x/common/layers/__init__.py
rinokeras/core/v1x/common/layers/activations.py
rinokeras/core/v1x/common/layers/autoregressive.py
rinokeras/core/v1x/common/layers/conv.py
rinokeras/core/v1x/common/layers/dropout.py
rinokeras/core/v1x/common/layers/inversion.py
rinokeras/core/v1x/common/layers/masking.py
rinokeras/core/v1x/common/layers/normalization.py
rinokeras/core/v1x/common/layers/position_embedding.py
rinokeras/core/v1x/common/layers/residual.py
rinokeras/core/v1x/common/layers/stack.py
rinokeras/core/v1x/models/__init__.py
rinokeras/core/v1x/models/glow.py
rinokeras/core/v1x/models/masked_rmc.py
rinokeras/core/v1x/models/rmc.py
rinokeras/core/v1x/models/qanet/__init__.py
rinokeras/core/v1x/models/qanet/qanet.py
rinokeras/core/v1x/models/qanet/qanet_attention.py
rinokeras/core/v1x/models/qanet/qanet_embedding.py
rinokeras/core/v1x/models/qanet/qanet_encoder.py
rinokeras/core/v1x/models/qanet/qanet_ff.py
rinokeras/core/v1x/models/resnet/__init__.py
rinokeras/core/v1x/models/resnet/resnet.py
rinokeras/core/v1x/models/rmc/__init__.py
rinokeras/core/v1x/models/rmc/masked_rmc.py
rinokeras/core/v1x/models/rmc/rmc.py
rinokeras/core/v1x/models/rmc/rmc_cell.py
rinokeras/core/v1x/models/transformer/__init__.py
rinokeras/core/v1x/models/transformer/transformer.py
rinokeras/core/v1x/models/transformer/transformer_attention.py
rinokeras/core/v1x/models/transformer/transformer_decoder.py
rinokeras-1.0.0.dist-info/METADATA
rinokeras-1.0.0.dist-info/RECORD
rinokeras-1.0.0.dist-info/WHEEL
rinokeras-1.0.0.dist-info/top_level.txt
