Metadata-Version: 2.1
Name: rinokeras
Version: 1.0.0
Summary: CannyLab Algorithms Repository
Home-page: https://github.com/CannyLab/rionkeras
Author: Roshan Rao, David Chan
Author-email: roshan_rao@berkeley.edu, davidchan@berkeley.edu
License: GNU GENERAL PUBLIC LICENSE
Requires-Dist: numpy
Requires-Dist: scipy
Requires-Dist: pytest
Requires-Dist: tqdm
Requires-Dist: h5py
Requires-Dist: packaging
Requires-Dist: typing
Requires-Dist: deprecation
Requires-Dist: coverage
Requires-Dist: codecov
Requires-Dist: pytest-cov
